wikibase_reconcile/__init__.py
wikibase_reconcile/client.py
wikibase_reconcile-0.2.0.dist-info/LICENSE
wikibase_reconcile-0.2.0.dist-info/METADATA
wikibase_reconcile-0.2.0.dist-info/WHEEL
wikibase_reconcile-0.2.0.dist-info/top_level.txt
wikibase_reconcile-0.2.0.dist-info/RECORD
