Metadata-Version: 2.1
Name: wikibase-reconcile
Version: 0.2.0
Summary: A concurrent client to reconcile entities against wikidata.
Author-email: Paul Balluff <paul.balluff@gmail.com>
Project-URL: Homepage, https://github.com/mrwunderbar666/wikibase_reconcile
Project-URL: Bug Tracker, https://github.com/mrwunderbar666/wikibase_reconcile/sampleproject/issues
Classifier: Programming Language :: Python :: 3
Classifier: License :: OSI Approved :: Apache Software License
Classifier: Operating System :: OS Independent
Requires-Python: >=3.7
License-File: LICENSE
Requires-Dist: requests
Requires-Dist: importlib-metadata ; python_version == "3.8"
